mpss_tools_36/__init__.py
mpss_tools_36/version.py
mpss_tools_36/api/data.py
mpss_tools_36/api/feedback.py
mpss_tools_36/api/sharer.py
mpss_tools_36/api/sharer_singleton.py
mpss_tools_36/api/task.py
mpss_tools_36/api/wrapper.py
mpss_tools_36/constant/data.py
mpss_tools_36/constant/feedback.py
mpss_tools_36/constant/generic.py
mpss_tools_36/constant/process.py
mpss_tools_36/constant/wrapper.py
mpss_tools_36/extension/chronos.py
mpss_tools_36/extension/data_class.py
mpss_tools_36/extension/multiprocessing_manager.py
mpss_tools_36/hint/data.py
mpss_tools_36/hint/feedback.py
mpss_tools_36/hint/process.py
mpss_tools_36/hint/serializer.py
mpss_tools_36/hint/wrapper.py
mpss_tools_36/task/chunk.py
mpss_tools_36/task/management.py
mpss_tools_36/task/numpy_sharing.py
mpss_tools_36/task/singleton_sharing.py
mpss_tools_36/type/line.py
mpss_tools_36/type/client/data.py
mpss_tools_36/type/client/sharer.py
mpss_tools_36/type/client/wrapper.py
mpss_tools_36/type/server/data.py
mpss_tools_36/type/server/feedback.py
mpss_tools_36/type/server/feedback_fake.py
mpss_tools_36/type/server/generic.py
mpss_tools_36/type/server/sharer.py
mpss_tools_36/type/server/wrapper.py
mpss_tools_36-2026.1.dist-info/METADATA
mpss_tools_36-2026.1.dist-info/WHEEL
mpss_tools_36-2026.1.dist-info/top_level.txt
mpss_tools_36-2026.1.dist-info/RECORD
