Metadata-Version: 2.4
Name: mpss-tools-36
Version: 2026.1
Summary: Sharing Python objects, Numpy arrays, and progress bars for Python's multiprocessing
Home-page: https://src.koda.cnrs.fr/eric.debreuve/mpss-tools-36/
Author: Eric Debreuve
Author-email: eric.debreuve@cnrs.fr
License: CeCILL-2.1
Project-URL: Documentation, https://src.koda.cnrs.fr/eric.debreuve/mpss-tools-36/-/wikis/home
Project-URL: Source, https://src.koda.cnrs.fr/eric.debreuve/mpss-tools-36/
Keywords: shared Numpy array,Rich progress bar,multiprocessing
Classifier: Topic :: Software Development
Classifier: Intended Audience :: Developers
Classifier: License :: OSI Approved :: CEA CNRS Inria Logiciel Libre License, version 2.1 (CeCILL-2.1)
Classifier: Programming Language :: Python :: 3
Classifier: Development Status :: 5 - Production/Stable
Requires-Python: >=3.11
Requires-Dist: logger_36
Requires-Dist: numpy
Dynamic: author
Dynamic: author-email
Dynamic: classifier
Dynamic: description
Dynamic: description-content-type
Dynamic: home-page
Dynamic: keywords
Dynamic: license
Dynamic: project-url
Dynamic: requires-dist
Dynamic: requires-python
Dynamic: summary
